{"name":"Graphsub","tagline":"A Javascript plugin for d3js. A resubale force directed graph with some useful features rolled in.","body":"<pre>\r\n                       _     ____        _     \r\n  __ _ _ __ __ _ _ __ | |__ / ___| _   _| |__  \r\n / _` | '__/ _` | '_ \\| '_ \\\\___ \\| | | | '_ \\ \r\n| (_| | | | (_| | |_) | | | |___) | |_| | |_) |\r\n \\__, |_|  \\__,_| .__/|_| |_|____/ \\__,_|_.__/ \r\n |___/          |_|                            \r\n\r\n</pre>\r\n\r\ngraphSub is a re-usable force directed chart for displaying connected data. Written in Javascript with the [d3js](http://d3js.org) library. It has some cool features rolled in.\r\n\r\n### Featues include:\r\n* Display graph subsets. Given a data-set with 1000+ nodes, displaying all nodes at once can clutter your  screen. With graphSub you can display only a subset of you data-set whilst being able to navigate through through the entire data-set with mouse clicks.\r\n* The search box feature allows you to quickly locate the node that you are interested in.\r\n* None over-lapping labels means that node labels do not obscure each other.\r\n* Works on touch screens.\r\n* The display automatically resizes upon browser window resizing.\r\n* The code uses an MVC architecture making development easier to manage.\r\n\r\n### Instructions:\r\n\r\nThe following code can be found at the end of static/js/graphsub.js please modify it to suit your needs.\r\nYour data must follow the format given in the example data-set. This can be found in /data/miserables.json\r\nMore information on d3s' force layouts can be found [here](https://github.com/mbostock/d3/wiki/Force-Layout#force).\r\n\r\n\r\n    `/*----------------------------------------------------------------------------`\r\n    `The code example below:`\r\n    `1. Loads the JSON data.`\r\n    `2. Sets the width to 760px. `\r\n    `3. Set the height to 500px.`\r\n    `4. Attaches the chart to the DOM element with id #chart`\r\n    `*/`\r\n\r\n    `d3.json(\"data/miserables.json\", function(error, graph) {`\r\n        `if (error) throw error;`\r\n\r\n        `// Parse JSON into the correct format if needed`\r\n\r\n        `var chart = d3.graphSub()`\r\n                      `.width(760)`\r\n                      `.height(500)`\r\n                      `.hops(2);`\r\n  \r\n        `d3.select(\"#chart\")`\r\n          `.datum(graph)`\r\n          `.call(chart); `\r\n    `}); `\r\n\r\n\r\nExample bl.ock.s used in the development of this graph:\r\n\r\n[Simple example of reusable d3 plugin](http://bl.ocks.org/cpbotha/5073718)\r\n\r\n[Force-based label placement](http://bl.ocks.org/MoritzStefaner/1377729)\r\n\r\n[Force-Directed Graph](http://bl.ocks.org/mbostock/4062045)\r\n\r\n[General Update Pattern, I](http://bl.ocks.org/mbostock/3808218)\r\n\r\n[General Update Pattern, II](http://bl.ocks.org/mbostock/3808221)\r\n\r\n[General Update Pattern, III](http://bl.ocks.org/mbostock/3808234)\r\n\r\n[Animating Changes in Force Diagram](http://bl.ocks.org/ericcoopey/6c602d7cb14b25c179a4)","google":"UA-39390892-6","note":"Don't delete this file! It's used internally to help with page regeneration."}